aiohttp_docs/__init__.py
aiohttp_docs/_constants.py
aiohttp_docs/_decorator.py
aiohttp_docs/_spec.py
aiohttp_docs/_types.py
aiohttp_docs-0.0.1.dist-info/licenses/LICENSE
aiohttp_docs-0.0.1.dist-info/WHEEL
aiohttp_docs-0.0.1.dist-info/METADATA
aiohttp_docs-0.0.1.dist-info/RECORD
