Metadata-Version: 2.4
Name: aiohttp-docs
Version: 0.0.1
Summary: API documentation for aiohttp server based on Pydantic models
Keywords: aiohttp,pydantic,swagger,openapi,documentation
Author: Mikhail Shagov
Author-email: Mikhail Shagov <mishaga@me.com>
License-Expression: MIT
License-File: LICENSE
Classifier: Development Status :: 1 - Planning
Classifier: Programming Language :: Python
Classifier: Programming Language :: Python :: 3
Classifier: Programming Language :: Python :: 3.11
Classifier: Programming Language :: Python :: 3.12
Classifier: Programming Language :: Python :: 3.13
Classifier: Intended Audience :: Developers
Classifier: Intended Audience :: Information Technology
Classifier: Operating System :: OS Independent
Classifier: Topic :: Software Development :: Libraries :: Python Modules
Requires-Dist: aiohttp>=3.12.15,<4.0.0
Requires-Dist: pydantic>=2.11.7,<3.0.0
Requires-Python: >=3.10
